module_tracker/__init__.py
module_tracker/__main__.py
module_tracker/analyzer.py
module_tracker/cli.py
module_tracker/tracker.py
module_tracker-0.0.3.data/scripts/module-tracker
module_tracker-0.0.3.dist-info/LICENSE
module_tracker-0.0.3.dist-info/METADATA
module_tracker-0.0.3.dist-info/WHEEL
module_tracker-0.0.3.dist-info/top_level.txt
module_tracker-0.0.3.dist-info/RECORD
