Metadata-Version: 2.1
Name: module-tracker
Version: 0.0.3
Summary: a tool that tracks dependencies in project
Home-page: https://github.com/jeongukjae/module-tracker.py
Author: Jeong Ukjae
Author-email: jeongukjae@gmail.com
License: MIT
Platform: UNKNOWN
Classifier: Development Status :: 1 - Planning
Classifier: License :: OSI Approved :: MIT License
Classifier: Programming Language :: Python
Classifier: Programming Language :: Python :: 3
Classifier: Programming Language :: Python :: 3.5
Classifier: Programming Language :: Python :: 3.6
Classifier: Programming Language :: Python :: 3.7
Classifier: Programming Language :: Python :: 3.8
Classifier: Operating System :: OS Independent
